lapet/__init__.py
lapet/__main__.py
lapet/gemma.py
lapet/handler.py
lapet/judge.py
lapet/llama.py
lapet/phi.py
lapet-0.9.4.dist-info/licenses/LICENSE
lapet-0.9.4.dist-info/METADATA
lapet-0.9.4.dist-info/WHEEL
lapet-0.9.4.dist-info/top_level.txt
lapet-0.9.4.dist-info/RECORD
