Metadata-Version: 2.4
Name: lapet
Version: 0.9.4
Summary: Library that makes it easier to evaluate the quality of LLM outputs
Author-email: Jonathan Eisenzopf <ironbraid74@gmail.com>
License: MIT
Project-URL: Homepage, https://github.com/eisenzopf/lapet
Project-URL: Issues, https://github.com/eisenzopf/lapet/issues
Keywords: llm
Classifier: Programming Language :: Python :: 3
Requires-Python: >=3.11
License-File: LICENSE
Requires-Dist: pandas
Requires-Dist: numpy
Requires-Dist: torch>=2.6.0
Requires-Dist: huggingface_hub>=0.23.0
Requires-Dist: transformers==4.52.3
Requires-Dist: openai>=1.0.0
Requires-Dist: importlib-metadata; python_version < "3.10"
Provides-Extra: cuda
Requires-Dist: flash_attn; extra == "cuda"
Requires-Dist: auto-gptq; extra == "cuda"
Requires-Dist: autoawq; extra == "cuda"
Dynamic: license-file
